ftm_columnstore/__init__.py
ftm_columnstore/cli.py
ftm_columnstore/engine.py
ftm_columnstore/phonetic.py
ftm_columnstore/settings.py
ftm_columnstore/statements.py
ftm_columnstore/store.py
ftm_columnstore-0.3.2.dist-info/LICENSE
ftm_columnstore-0.3.2.dist-info/METADATA
ftm_columnstore-0.3.2.dist-info/WHEEL
ftm_columnstore-0.3.2.dist-info/entry_points.txt
ftm_columnstore-0.3.2.dist-info/RECORD
