Metadata-Version: 2.1
Name: ftm-columnstore
Version: 0.3.2
Summary: Column store implementation for ftm data based on clickhouse
Home-page: https://github.com/investigativedata/ftm-columnstore
License: GPL3
Author: Simon Wörpel
Author-email: simon@investigativedata.org
Requires-Python: >=3.11,<4
Classifier: Intended Audience :: Developers
Classifier: License :: Other/Proprietary License
Classifier: Operating System :: OS Independent
Classifier: Programming Language :: Python
Classifier: Programming Language :: Python :: 3
Classifier: Programming Language :: Python :: 3.11
Classifier: Programming Language :: Python :: 3.12
Requires-Dist: banal (>=1.0.6,<2.0.0)
Requires-Dist: clickhouse-driver[numpy] (>=0.2.8,<0.3.0)
Requires-Dist: ftmq (>=0.6.12,<0.7.0)
Requires-Dist: libindic-soundex (>=1.0.2,<2.0.0)
Requires-Dist: libindic-utils (>=1.0.3,<2.0.0)
Requires-Dist: metaphone (>=0.6,<0.7)
Requires-Dist: pandas (>=2.2.2,<3.0.0)
Requires-Dist: pyicu (>=2.13.1,<3.0.0)
Requires-Dist: rich (>=13.7.1,<14.0.0)
Requires-Dist: typer (>=0.12.3,<0.13.0)
Project-URL: Bug Tracker, https://github.com/investigativedata/ftm-columnstore/issues
Project-URL: Documentation, https://github.com/investigativedata/ftm-columnstore
Project-URL: Repository, https://github.com/investigativedata/ftm-columnstore
